os_utils/__init__.py
os_utils/logging_utils.py
os_utils/operations.py
os_utils/path.py
os_utils-0.2.0.dist-info/METADATA
os_utils-0.2.0.dist-info/WHEEL
os_utils-0.2.0.dist-info/licenses/LICENCE
os_utils-0.2.0.dist-info/RECORD
