Metadata-Version: 2.4
Name: os_utils
Version: 0.2.0
Summary: os utils to reduce code copy paste
Project-URL: Homepage, https://github.com/ahcub/os_utils
Project-URL: Repository, https://github.com/ahcub/os_utils
Author-email: Alex Buchkovsky <olex.buchkovsky@gmail.com>
License-File: LICENCE
Keywords: dirs,files,logging,path
Classifier: License :: OSI Approved :: MIT License
Classifier: Operating System :: OS Independent
Classifier: Programming Language :: Python :: 3
Requires-Python: >=3.14
